CHANGES.txt
setup.py
oc_wp.egg-info/PKG-INFO
oc_wp.egg-info/SOURCES.txt
oc_wp.egg-info/dependency_links.txt
oc_wp.egg-info/entry_points.txt
oc_wp.egg-info/namespace_packages.txt
oc_wp.egg-info/not-zip-safe
oc_wp.egg-info/requires.txt
oc_wp.egg-info/top_level.txt
opencore/__init__.py
opencore/wordpress/README.txt
opencore/wordpress/__init__.py
opencore/wordpress/configure.zcml
opencore/wordpress/featurelet.py
opencore/wordpress/interfaces.py
opencore/wordpress/subscribers.py
opencore/wordpress/test-directive.zcml
opencore/wordpress/tests.py
opencore/wordpress/browser/__init__.py
opencore/wordpress/browser/configure.zcml
opencore/wordpress/browser/views.py
opencore/wordpress/feed/__init__.py
opencore/wordpress/feed/blog.py
opencore/wordpress/feed/blog_blank_slate.pt
opencore/wordpress/feed/configure.zcml
opencore/wordpress/feed/wordpress.py