Metadata-Version: 1.0
Name: oc-wp
Version: 0.3
Summary: opencore wordpress client package
Home-page: http://coactivate.org/projects/opencore
Author: The OpenCore community
Author-email: opencore-dev@lists.coactivate.org
License: GPL
Platform: UNKNOWN
Classifier: Framework :: Plone
Classifier: Framework :: Zope2
Classifier: Framework :: Zope3
Classifier: Programming Language :: Python
Classifier: Topic :: Software Development :: Libraries :: Python Modules
